{
	"name": "pipeline1",
	"properties": {
		"activities": [
			{
				"name": "InsertarPersona",
				"type": "SqlServerStoredProcedure",
				"dependsOn": [
					{
						"activity": "ForEach1",
						"dependencyConditions": [
							"Succeeded"
						]
					}
				],
				"policy": {
					"timeout": "7.00:00:00",
					"retry": 0,
					"retryIntervalInSeconds": 30,
					"secureOutput": false,
					"secureInput": false
				},
				"userProperties": [],
				"typeProperties": {
					"storedProcedureName": "[dbo].[uspInsertardimPersonas]"
				},
				"linkedServiceName": {
					"referenceName": "AzureSqlDatabase1",
					"type": "LinkedServiceReference"
				}
			},
			{
				"name": "EliminarFueteRaw",
				"type": "SqlServerStoredProcedure",
				"dependsOn": [],
				"policy": {
					"timeout": "7.00:00:00",
					"retry": 0,
					"retryIntervalInSeconds": 30,
					"secureOutput": false,
					"secureInput": false
				},
				"userProperties": [],
				"typeProperties": {
					"storedProcedureName": "[dbo].[uspEliminarFuenteRaw]"
				},
				"linkedServiceName": {
					"referenceName": "AzureSqlDatabase1",
					"type": "LinkedServiceReference"
				}
			},
			{
				"name": "InsertarFactMetrics",
				"type": "SqlServerStoredProcedure",
				"dependsOn": [
					{
						"activity": "InsertarPersona",
						"dependencyConditions": [
							"Succeeded"
						]
					}
				],
				"policy": {
					"timeout": "7.00:00:00",
					"retry": 0,
					"retryIntervalInSeconds": 30,
					"secureOutput": false,
					"secureInput": false
				},
				"userProperties": [],
				"typeProperties": {
					"storedProcedureName": "[dbo].[uspInsertarFactMetrics]"
				},
				"linkedServiceName": {
					"referenceName": "AzureSqlDatabase1",
					"type": "LinkedServiceReference"
				}
			},
			{
				"name": "InsertarDimSorce",
				"type": "SqlServerStoredProcedure",
				"dependsOn": [
					{
						"activity": "InsertarFactMetrics",
						"dependencyConditions": [
							"Succeeded"
						]
					}
				],
				"policy": {
					"timeout": "7.00:00:00",
					"retry": 0,
					"retryIntervalInSeconds": 30,
					"secureOutput": false,
					"secureInput": false
				},
				"userProperties": [],
				"typeProperties": {
					"storedProcedureName": "[dbo].[uspDimSource]"
				},
				"linkedServiceName": {
					"referenceName": "AzureSqlDatabase1",
					"type": "LinkedServiceReference"
				}
			},
			{
				"name": "TraerArchivos",
				"type": "GetMetadata",
				"dependsOn": [
					{
						"activity": "EliminarFueteRaw",
						"dependencyConditions": [
							"Succeeded"
						]
					}
				],
				"policy": {
					"timeout": "7.00:00:00",
					"retry": 0,
					"retryIntervalInSeconds": 30,
					"secureOutput": false,
					"secureInput": false
				},
				"userProperties": [],
				"typeProperties": {
					"dataset": {
						"referenceName": "ds_archivos",
						"type": "DatasetReference"
					},
					"fieldList": [
						"childItems"
					],
					"storeSettings": {
						"type": "AzureBlobStorageReadSettings",
						"enablePartitionDiscovery": false
					},
					"formatSettings": {
						"type": "DelimitedTextReadSettings"
					}
				}
			},
			{
				"name": "ForEach1",
				"type": "ForEach",
				"dependsOn": [
					{
						"activity": "TraerArchivos",
						"dependencyConditions": [
							"Succeeded"
						]
					}
				],
				"userProperties": [],
				"typeProperties": {
					"items": {
						"value": "@activity('TraerArchivos').output.ChildItems",
						"type": "Expression"
					},
					"activities": [
						{
							"name": "CargarCsvEnBD",
							"type": "Copy",
							"dependsOn": [],
							"policy": {
								"timeout": "7.00:00:00",
								"retry": 0,
								"retryIntervalInSeconds": 30,
								"secureOutput": false,
								"secureInput": false
							},
							"userProperties": [],
							"typeProperties": {
								"source": {
									"type": "DelimitedTextSource",
									"storeSettings": {
										"type": "AzureBlobStorageReadSettings",
										"recursive": true,
										"wildcardFileName": {
											"value": "@item().name",
											"type": "Expression"
										},
										"enablePartitionDiscovery": false
									},
									"formatSettings": {
										"type": "DelimitedTextReadSettings"
									}
								},
								"sink": {
									"type": "AzureSqlSink"
								},
								"enableStaging": false,
								"translator": {
									"type": "TabularTranslator",
									"mappings": [
										{
											"source": {
												"type": "String",
												"ordinal": 1
											},
											"sink": {
												"name": "profile.identity",
												"type": "String",
												"physicalType": "varchar"
											}
										},
										{
											"source": {
												"type": "String",
												"ordinal": 2
											},
											"sink": {
												"name": "profile.all_identities",
												"type": "String",
												"physicalType": "varchar"
											}
										},
										{
											"source": {
												"type": "String",
												"ordinal": 3
											},
											"sink": {
												"name": "profile.platform",
												"type": "String",
												"physicalType": "varchar"
											}
										},
										{
											"source": {
												"type": "String",
												"ordinal": 4
											},
											"sink": {
												"name": "profile.phone",
												"type": "String",
												"physicalType": "varchar"
											}
										},
										{
											"source": {
												"type": "String",
												"ordinal": 5
											},
											"sink": {
												"name": "profile.name",
												"type": "String",
												"physicalType": "varchar"
											}
										},
										{
											"source": {
												"type": "String",
												"ordinal": 6
											},
											"sink": {
												"name": "profile.email",
												"type": "String",
												"physicalType": "varchar"
											}
										},
										{
											"source": {
												"type": "String",
												"ordinal": 7
											},
											"sink": {
												"name": "deviceInfo.make",
												"type": "String",
												"physicalType": "varchar"
											}
										},
										{
											"source": {
												"type": "String",
												"ordinal": 8
											},
											"sink": {
												"name": "deviceInfo.dpi",
												"type": "String",
												"physicalType": "varchar"
											}
										},
										{
											"source": {
												"type": "String",
												"ordinal": 9
											},
											"sink": {
												"name": "deviceInfo.dimensions.width",
												"type": "String",
												"physicalType": "varchar"
											}
										},
										{
											"source": {
												"type": "String",
												"ordinal": 10
											},
											"sink": {
												"name": "deviceInfo.dimensions.height",
												"type": "String",
												"physicalType": "varchar"
											}
										},
										{
											"source": {
												"type": "String",
												"ordinal": 11
											},
											"sink": {
												"name": "eventProps.wzrk_pid",
												"type": "String",
												"physicalType": "varchar"
											}
										},
										{
											"source": {
												"type": "String",
												"ordinal": 12
											},
											"sink": {
												"name": "eventProps.wzrk_cid",
												"type": "String",
												"physicalType": "varchar"
											}
										},
										{
											"source": {
												"type": "String",
												"ordinal": 13
											},
											"sink": {
												"name": "eventProps.wzrk_dt",
												"type": "String",
												"physicalType": "varchar"
											}
										}
									],
									"typeConversion": true,
									"typeConversionSettings": {
										"allowDataTruncation": true,
										"treatBooleanAsNumber": false
									}
								}
							},
							"inputs": [
								{
									"referenceName": "ds_archivos",
									"type": "DatasetReference"
								}
							],
							"outputs": [
								{
									"referenceName": "bdFuenteRaw",
									"type": "DatasetReference"
								}
							]
						}
					]
				}
			}
		],
		"annotations": []
	}
}